pyETA/__init__.py
pyETA/application.py
pyETA/cli.py
pyETA/components/__init__.py
pyETA/components/mock.py
pyETA/components/reader.py
pyETA/components/track.py
pyETA/components/utils.py
pyETA/components/validate.py
pyETA/components/window.py
pyeta_toolbox-0.1.0.dist-info/LICENSE
pyeta_toolbox-0.1.0.dist-info/METADATA
pyeta_toolbox-0.1.0.dist-info/WHEEL
pyeta_toolbox-0.1.0.dist-info/entry_points.txt
pyeta_toolbox-0.1.0.dist-info/RECORD
