Metadata-Version: 2.1
Name: pyETA-toolbox
Version: 0.1.0
Summary: This toolbox provides a realtime visualization of eye tracking data to be used for designing passive BCI system.
Home-page: https://github.com/VinayIN/pyETA-toolbox.git
License: GPL-3.0
Keywords: eyetracker,tobii,mock tobii,passiveBCI,real-time eye tracking,tobii-research
Author: Binay Kumar Pradhan
Author-email: bpradhan.asli@gmail.com
Requires-Python: >=3.10,<3.11
Classifier: License :: OSI Approved :: GNU General Public License v3 (GPLv3)
Classifier: Programming Language :: Python :: 3
Classifier: Programming Language :: Python :: 3.10
Requires-Dist: click (>=8.1.8,<9.0.0)
Requires-Dist: mne-lsl (==1.6.0)
Requires-Dist: numpy (>=2.2.2,<3.0.0)
Requires-Dist: pandas (>=2.2.3,<3.0.0)
Requires-Dist: pylsl (>=1.17.6,<2.0.0)
Requires-Dist: pynput (>=1.7.7,<2.0.0)
Requires-Dist: pyqt6 (>=6.8.0,<7.0.0)
Requires-Dist: tobii-research (==1.11.0)
Project-URL: Documentation, https://vinayin.gitbook.io/pyeta/
Project-URL: Repository, https://github.com/VinayIN/pyETA-toolbox.git
